bluecat/__init__.py
bluecat/bluecat.py
bluecat-0.0.2.dist-info/LICENSE
bluecat-0.0.2.dist-info/METADATA
bluecat-0.0.2.dist-info/WHEEL
bluecat-0.0.2.dist-info/top_level.txt
bluecat-0.0.2.dist-info/RECORD
